sorts_pr/__init__.py
sorts_pr/bubble_sort.py
sorts_pr/insertion_sort.py
sorts_pr/quick_sort.py
sorts_pr/selection_sort.py
sorts_pr/sorting_app.py
sorts_pr-0.1.0.dist-info/METADATA
sorts_pr-0.1.0.dist-info/WHEEL
sorts_pr-0.1.0.dist-info/top_level.txt
sorts_pr-0.1.0.dist-info/RECORD
